ledger_importer/__init__.py
ledger_importer/__main__.py
ledger_importer/config.py
ledger_importer/transaction.py
ledger_importer/transactions_handler.py
ledger_importer-0.5.2.dist-info/entry_points.txt
ledger_importer-0.5.2.dist-info/WHEEL
ledger_importer-0.5.2.dist-info/METADATA
ledger_importer-0.5.2.dist-info/RECORD
