Metadata-Version: 2.1
Name: ledger-importer
Version: 0.5.2
Summary: ledger_importer is a csv-to-ledger importer that can be configured in Python.
Home-page: https://github.com/volnt/ledger_importer
Author: Florent Espanet
Author-email: florent.esp@gmail.com
Requires-Python: >=3.8,<4.0
Classifier: Programming Language :: Python :: 3
Classifier: Programming Language :: Python :: 3.10
Classifier: Programming Language :: Python :: 3.8
Classifier: Programming Language :: Python :: 3.9
Requires-Dist: typer (>=0.4.1,<0.5.0)
Project-URL: Repository, https://github.com/volnt/ledger_importer
